LICENSE
README.md
setup.cfg
setup.py
pyplejd/__init__.py
pyplejd/const.py
pyplejd/errors.py
pyplejd.egg-info/PKG-INFO
pyplejd.egg-info/SOURCES.txt
pyplejd.egg-info/dependency_links.txt
pyplejd.egg-info/requires.txt
pyplejd.egg-info/top_level.txt
pyplejd/ble/__init__.py
pyplejd/ble/ble_characteristics.py
pyplejd/ble/crypto.py
pyplejd/ble/debug.py
pyplejd/ble/lastdata.py
pyplejd/ble/lightlevel.py
pyplejd/ble/payload_encode.py
pyplejd/cloud/__init__.py
pyplejd/cloud/site_details.py
pyplejd/cloud/site_list.py
pyplejd/interface/__init__.py
pyplejd/interface/device_type.py
pyplejd/interface/plejd_button.py
pyplejd/interface/plejd_cover.py
pyplejd/interface/plejd_device.py
pyplejd/interface/plejd_fellowship_follower.py
pyplejd/interface/plejd_hardware.py
pyplejd/interface/plejd_light.py
pyplejd/interface/plejd_motion_sensor.py
pyplejd/interface/plejd_relay.py
pyplejd/interface/plejd_scene.py
pyplejd/interface/plejd_thermostat.py