Metadata-Version: 2.1
Name: pyplejd
Version: 0.20.1
Summary: A python library for communicating with Plejd devices via bluetooth
Home-page: https://github.com/thomasloven/pyplejd
Download-URL: https://github.com/thomasloven/pyplejd/archive/v0.20.1.tar.gz
Author: Thomas Lovén
Author-email: thomasloven@gmail.com
License: MIT
Keywords: plejd,bluetooth,homeassistant
Requires-Python: >=3.10
License-File: LICENSE
Requires-Dist: aiohttp
Requires-Dist: bleak
Requires-Dist: bleak_retry_connector
Requires-Dist: pydantic
